my_complex_app/__init__.py
my_complex_app/calc.py
my_complex_app-0.1.0.dist-info/METADATA
my_complex_app-0.1.0.dist-info/WHEEL
my_complex_app-0.1.0.dist-info/top_level.txt
my_complex_app-0.1.0.dist-info/RECORD
