Metadata-Version: 2.1
Name: my-complex-app
Version: 0.1.0
Summary: To add the given two complex numbers
Home-page: UNKNOWN
License: UNKNOWN
Platform: UNKNOWN
Requires-Python: >=3.7
Requires-Dist: wheel
Requires-Dist: twine
